quspin_qite/__init__.py
quspin_qite/utils.py
quspin_qite/algo/__init__.py
quspin_qite/algo/qite.py
quspin_qite/algo/variational_algorithm.py
quspin_qite/algo/vqite.py
quspin_qite/opt/__init__.py
quspin_qite/opt/optimizer.py
quspin_qite/opt/solver.py
quspin_qite/phys/__init__.py
quspin_qite/phys/heisenberg_lr.py
quspin_qite/phys/heisenberg_sr.py
quspin_qite/phys/ising.py
quspin_qite/phys/maxcut.py
quspin_qite/phys/physics_system.py
quspin_qite-0.0.3.dist-info/LICENSE
quspin_qite-0.0.3.dist-info/METADATA
quspin_qite-0.0.3.dist-info/WHEEL
quspin_qite-0.0.3.dist-info/top_level.txt
quspin_qite-0.0.3.dist-info/RECORD
