Metadata-Version: 2.1
Name: quspin-qite
Version: 0.0.3
Summary: Variatioanl Quantum Imaginary Algorithms
Home-page: https://github.com/JiahaoYao/QITE_CD
Author: Jimmy
Author-email: jiahaoyao.math@gmail.com
License: MIT
Keywords: quantum computing,variational quantum algorithms,QITE,quantum machine learning,Reinforcement Learning,Quspin
Classifier: Development Status :: 4 - Beta
Classifier: Intended Audience :: Developers
Classifier: Topic :: Scientific/Engineering :: Artificial Intelligence
Classifier: License :: OSI Approved :: MIT License
Classifier: Programming Language :: Python :: 3.6
License-File: LICENSE
Requires-Dist: icecream (==2.1.2)
Requires-Dist: matplotlib (==3.5.1)
Requires-Dist: numpy (==1.21.2)
Requires-Dist: scipy (==1.7.3)
Requires-Dist: snoop (==0.4.1)
Requires-Dist: sysflow (==0.1.15)
Requires-Dist: tqdm (==4.64.0)
